{
    "restricoes": {
        "Fabrício Castanheiro": [
            "Cauana da Silva",
            "Lucas Schutz",
            "Eloá Schutz",
            "Marzinho (Tuntuna)",
            "Sandra Mara",
            "Namir",
            "Duduca"
        ],
        "Daiane Meyer Castanheiro": [
            "Cauana da Silva",
            "Lucas Schutz",
            "Eloá Schutz",
            "Marzinho (Tuntuna)",
            "Sandra Mara",
            "Namir",
            "Duduca"
        ],
        "Patricia": [
            "Cauana da Silva",
            "Lucas Schutz",
            "Eloá Schutz",
            "Marzinho (Tuntuna)",
            "Sandra Mara",
            "Namir",
            "Duduca"
        ],
        "Iasmim": [
            "Cauana da Silva",
            "Lucas Schutz",
            "Eloá Schutz",
            "Marzinho (Tuntuna)",
            "Sandra Mara",
            "Namir",
            "Duduca"
        ]
    }
}